<?xml version="1.0" encoding="UTF-8"?>
<!DOCTYPE suite SYSTEM "http://testng.org/testng-1.0.dtd">
<suite thread-count="2" name="Coal Application Automation Test Suite"parallel="classes">

	 <listeners>
		<listener class-name="com.qa.ExtentReporterListener.ExtentReporterNG" />
	</listeners>

	<test name="CoalTest">
	
		<classes>
			<class name="com.qa.testcases.LoginPageTest"></class>
			<class name="com.qa.testcases.CurrentEMDTest"></class>	
			<class name="com.qa.testcases.BidHistoryTest"></class>	
			<class name="com.qa.testcases.CurrentStatusScreenTest"></class> 		
		</classes>
		
	</test>
	
</suite>